nmrml2isa_qt/__init__.py
nmrml2isa_qt/__main__.py
nmrml2isa_qt/contact.py
nmrml2isa_qt/main.py
nmrml2isa_qt/ols.py
nmrml2isa_qt/parserprogress.py
nmrml2isa_qt/scrapers.py
nmrml2isa_qt/usermeta.py
nmrml2isa_qt/ontologies/pro.json
nmrml2isa_qt/ontologies/pso.json
nmrml2isa_qt/qt/__init__.py
nmrml2isa_qt/qt/contact.py
nmrml2isa_qt/qt/help.py
nmrml2isa_qt/qt/main.py
nmrml2isa_qt/qt/ols.py
nmrml2isa_qt/qt/progress.py
nmrml2isa_qt/qt/resources_rc.py
nmrml2isa_qt/qt/usermeta.py
nmrml2isa_qt-0.1.3.dist-info/DESCRIPTION.rst
nmrml2isa_qt-0.1.3.dist-info/METADATA
nmrml2isa_qt-0.1.3.dist-info/RECORD
nmrml2isa_qt-0.1.3.dist-info/WHEEL
nmrml2isa_qt-0.1.3.dist-info/entry_points.txt
nmrml2isa_qt-0.1.3.dist-info/metadata.json
nmrml2isa_qt-0.1.3.dist-info/top_level.txt
