Metadata-Version: 2.0
Name: nmrml2isa-qt
Version: 0.1.3
Summary: A PyQt interface for nmrml2isa parser.
Home-page: https://github.com/althonos/nmrzml2isa-qt
Author: Martin Larralde
Author-email: martin.larralde@ens-cachan.fr
License: GPLv3
Keywords: Metabolomics,Mass spectrometry,Imaging Mass Spectrometry,metabolites,ISA Tab,imzML,parsing
Platform: UNKNOWN
Classifier: Programming Language :: Python
Classifier: Programming Language :: Python :: 3
Classifier: Topic :: Text Processing :: Markup :: XML
Classifier: Topic :: Scientific/Engineering :: Bio-Informatics
Classifier: Topic :: Utilities
Classifier: Operating System :: OS Independent
Requires-Dist: PyQt5
Requires-Dist: nmrml2isa
